fpga/hdl/voxel_downsampler.vhd
library ieee;
use ieee.std_logic_1164.all;
use ieee.numeric_std.all;

entity voxel_downsampler is
  generic (
    DATA_WIDTH : integer := 32; -- Q16.16 Fixed point format
    SHIFT_BITS : integer := 14; -- Voxel Resolution Shift (e.g., 2^14 = 0.25m bin)
    RAM_ADDR_BITS : integer := 10 -- 1024-entry hash occupancy table
  );
  port (
    clk           : in  std_logic;
    rst_n         : in  std_logic;
    
    -- Sync signal to clear occupancy map at frame boundaries
    frame_sync    : in  std_logic;

    -- Incoming AXI4-Stream Point Channel
    s_axis_tdata_x : in  std_logic_vector(DATA_WIDTH-1 downto 0);
    s_axis_tdata_y : in  std_logic_vector(DATA_WIDTH-1 downto 0);
    s_axis_tdata_z : in  std_logic_vector(DATA_WIDTH-1 downto 0);
    s_axis_tvalid  : in  std_logic;
    s_axis_tready  : out std_logic;

    -- Downsampled Outgoing AXI4-Stream Point Channel
    m_axis_tdata_x : out std_logic_vector(DATA_WIDTH-1 downto 0);
    m_axis_tdata_y : out std_logic_vector(DATA_WIDTH-1 downto 0);
    m_axis_tdata_z : out std_logic_vector(DATA_WIDTH-1 downto 0);
    m_axis_tvalid  : out std_logic;
    m_axis_tready  : in  std_logic
  );
end entity voxel_downsampler;

architecture rtl of voxel_downsampler is

  -- Occupancy Table RAM Signals
  type ram_type is array (0 to (2**RAM_ADDR_BITS)-1) of std_logic;
  signal occupancy_ram : ram_type := (others => '0');

  -- Pipeline Registers
  signal voxel_hash   : unsigned(RAM_ADDR_BITS-1 downto 0);
  signal x_reg, y_reg, z_reg : std_logic_vector(DATA_WIDTH-1 downto 0);
  signal valid_reg    : std_logic;
  signal is_occupied  : std_logic;

begin

  -- Pass-through ready handshake
  s_axis_tready <= m_axis_tready;

  -- Pipeline Stage 1: Spatial Hash Calculation & Occupancy Check
  process(clk, rst_n)
    variable bin_x, bin_y, bin_z : unsigned(RAM_ADDR_BITS-1 downto 0);
    variable combined_hash      : unsigned(RAM_ADDR_BITS-1 downto 0);
    
    -- Intermediate slices to enforce valid VHDL type conversion rules
    variable slice_x, slice_y, slice_z : std_logic_vector(RAM_ADDR_BITS-1 downto 0);
  begin
    if rst_n = '0' then
      x_reg        <= (others => '0');
      y_reg        <= (others => '0');
      z_reg        <= (others => '0');
      valid_reg    <= '0';
      voxel_hash   <= (others => '0');
      is_occupied  <= '0';
      occupancy_ram <= (others => '0');
    elsif rising_edge(clk) then
      
      -- Clear occupancy RAM on frame boundary sync
      if frame_sync = '1' then
        occupancy_ram <= (others => '0');
      end if;

      if (s_axis_tvalid = '1' and m_axis_tready = '1') then
        
        -- 1. Slice bit vectors first
        slice_x := s_axis_tdata_x(SHIFT_BITS + RAM_ADDR_BITS - 1 downto SHIFT_BITS);
        slice_y := s_axis_tdata_y(SHIFT_BITS + RAM_ADDR_BITS - 1 downto SHIFT_BITS);
        slice_z := s_axis_tdata_z(SHIFT_BITS + RAM_ADDR_BITS - 1 downto SHIFT_BITS);

        -- 2. Convert cleanly without illegal chained operations
        bin_x := unsigned(slice_x);
        bin_y := unsigned(slice_y);
        bin_z := unsigned(slice_z);

        -- XOR Spatial Hashing function for 3D grid address
        combined_hash := bin_x xor bin_y xor bin_z;
        voxel_hash    <= combined_hash;

        -- Register incoming point coordinate data
        x_reg <= s_axis_tdata_x;
        y_reg <= s_axis_tdata_y;
        z_reg <= s_axis_tdata_z;

        -- Check occupancy RAM status
        if occupancy_ram(to_integer(combined_hash)) = '1' then
          is_occupied <= '1'; -- Point falls in an occupied bin -> Drop
          valid_reg   <= '0';
        else
          is_occupied <= '0'; -- First point in bin -> Pass through & set bit
          valid_reg   <= '1';
          occupancy_ram(to_integer(combined_hash)) <= '1';
        end if;
      else
        valid_reg <= '0';
      end if;
    end if;
  end process;

  -- Pipeline Stage 2: Streaming Outputs
  m_axis_tdata_x <= x_reg;
  m_axis_tdata_y <= y_reg;
  m_axis_tdata_z <= z_reg;
  m_axis_tvalid  <= valid_reg;

end architecture rtl;

fpga/tb/tb_voxel_downsampler.vhd
library ieee;
use ieee.std_logic_1164.all;
use ieee.numeric_std.all;
use std.env.finish;  -- <--- Add std.env package

entity tb_voxel_downsampler is
end entity tb_voxel_downsampler;

architecture sim of tb_voxel_downsampler is

  constant CLK_PERIOD : time := 10 ns; -- 100 MHz clock
  constant DATA_WIDTH : integer := 32;

  signal clk           : std_logic := '0';
  signal rst_n         : std_logic := '0';
  signal frame_sync    : std_logic := '0';

  signal s_axis_tdata_x, s_axis_tdata_y, s_axis_tdata_z : std_logic_vector(DATA_WIDTH-1 downto 0) := (others => '0');
  signal s_axis_tvalid  : std_logic := '0';
  signal s_axis_tready  : std_logic;

  signal m_axis_tdata_x, m_axis_tdata_y, m_axis_tdata_z : std_logic_vector(DATA_WIDTH-1 downto 0);
  signal m_axis_tvalid  : std_logic;
  signal m_axis_tready  : std_logic := '1';

begin

  -- Instantiate DUT
  uut: entity work.voxel_downsampler
    generic map (
      DATA_WIDTH => 32,
      SHIFT_BITS => 14,
      RAM_ADDR_BITS => 10
    )
    port map (
      clk => clk, rst_n => rst_n, frame_sync => frame_sync,
      s_axis_tdata_x => s_axis_tdata_x, s_axis_tdata_y => s_axis_tdata_y, s_axis_tdata_z => s_axis_tdata_z,
      s_axis_tvalid => s_axis_tvalid, s_axis_tready => s_axis_tready,
      m_axis_tdata_x => m_axis_tdata_x, m_axis_tdata_y => m_axis_tdata_y, m_axis_tdata_z => m_axis_tdata_z,
      m_axis_tvalid => m_axis_tvalid, m_axis_tready => m_axis_tready
    );

  -- Clock Generator
  clk <= not clk after CLK_PERIOD / 2;

  -- Stimulus Process
  stim_proc: process
  begin
    -- Reset sequence
    rst_n <= '0';
    wait for 20 ns;
    rst_n <= '1';
    wait for 10 ns;

    -- Point 1: Bin A (X=1.0, Y=2.0, Z=0.5)
    s_axis_tdata_x <= x"00010000";
    s_axis_tdata_y <= x"00020000";
    s_axis_tdata_z <= x"00008000";
    s_axis_tvalid  <= '1';
    wait for CLK_PERIOD;

    -- Point 2: Duplicate in Bin A (X=1.01, Y=2.01, Z=0.51 -> Should be DROPPED)
    s_axis_tdata_x <= x"00010050";
    s_axis_tdata_y <= x"00020050";
    s_axis_tdata_z <= x"00008050";
    s_axis_tvalid  <= '1';
    wait for CLK_PERIOD;

    -- Point 3: Bin B (X=10.0, Y=5.0, Z=1.0 -> Should PASS)
    s_axis_tdata_x <= x"000A0000";
    s_axis_tdata_y <= x"00050000";
    s_axis_tdata_z <= x"00010000";
    s_axis_tvalid  <= '1';
    wait for CLK_PERIOD;

    s_axis_tvalid <= '0';
    wait for 50 ns;

    -- Clean simulation termination (VHDL-2008 standard)
    report "Simulation Finished Successfully!";
    finish;  -- <--- Clean exit call
  end process;

end architecture sim;

fpga/sim/downsampler_tb.vcd
$date
  Sun Aug  2 14:18:32 2026
$end
$version
  GHDL v0
$end
$timescale
  1 fs
$end
$scope module standard $end
$upscope $end
$scope module textio $end
$upscope $end
$scope module std_logic_1164 $end
$upscope $end
$scope module numeric_std $end
$upscope $end
$scope module env $end
$upscope $end
$scope module tb_voxel_downsampler $end
$var reg 1 ! clk $end
$var reg 1 " rst_n $end
$var reg 1 # frame_sync $end
$var reg 32 $ s_axis_tdata_x[31:0] $end
$var reg 32 % s_axis_tdata_y[31:0] $end
$var reg 32 & s_axis_tdata_z[31:0] $end
$var reg 1 ' s_axis_tvalid $end
$var reg 1 ( s_axis_tready $end
$var reg 32 ) m_axis_tdata_x[31:0] $end
$var reg 32 * m_axis_tdata_y[31:0] $end
$var reg 32 + m_axis_tdata_z[31:0] $end
$var reg 1 , m_axis_tvalid $end
$var reg 1 - m_axis_tready $end
$scope module uut $end
$var reg 1 . clk $end
$var reg 1 / rst_n $end
$var reg 1 0 frame_sync $end
$var reg 32 1 s_axis_tdata_x[31:0] $end
$var reg 32 2 s_axis_tdata_y[31:0] $end
$var reg 32 3 s_axis_tdata_z[31:0] $end
$var reg 1 4 s_axis_tvalid $end
$var reg 1 5 s_axis_tready $end
$var reg 32 6 m_axis_tdata_x[31:0] $end
$var reg 32 7 m_axis_tdata_y[31:0] $end
$var reg 32 8 m_axis_tdata_z[31:0] $end
$var reg 1 9 m_axis_tvalid $end
$var reg 1 : m_axis_tready $end
$var reg 1024 ; occupancy_ram[0:1023] $end
$var reg 10 < voxel_hash[9:0] $end
$var reg 32 = x_reg[31:0] $end
$var reg 32 > y_reg[31:0] $end
$var reg 32 ? z_reg[31:0] $end
$var reg 1 @ valid_reg $end
$var reg 1 A is_occupied $end
$upscope $end
$upscope $end
$enddefinitions $end
#0
0!
0"
0#
b00000000000000000000000000000000 $
b00000000000000000000000000000000 %
b00000000000000000000000000000000 &
0'
1(
b00000000000000000000000000000000 )
b00000000000000000000000000000000 *
b00000000000000000000000000000000 +
0,
1-
0.
0/
00
b00000000000000000000000000000000 1
b00000000000000000000000000000000 2
b00000000000000000000000000000000 3
04
15
b00000000000000000000000000000000 6
b00000000000000000000000000000000 7
b00000000000000000000000000000000 8
09
1:
b0000000000000000000000000000000000000000000000000000000000000000000000000000000000000000000000000000000000000000000000000000000000000000000000000000000000000000000000000000000000000000000000000000000000000000000000000000000000000000000000000000000000000000000000000000000000000000000000000000000000000000000000000000000000000000000000000000000000000000000000000000000000000000000000000000000000000000000000000000000000000000000000000000000000000000000000000000000000000000000000000000000000000000000000000000000000000000000000000000000000000000000000000000000000000000000000000000000000000000000000000000000000000000000000000000000000000000000000000000000000000000000000000000000000000000000000000000000000000000000000000000000000000000000000000000000000000000000000000000000000000000000000000000000000000000000000000000000000000000000000000000000000000000000000000000000000000000000000000000000000000000000000000000000000000000000000000000000000000000000000000000000000000000000000000000000000000000000000000000000000000000 ;
b0000000000 <
b00000000000000000000000000000000 =
b00000000000000000000000000000000 >
b00000000000000000000000000000000 ?
0@
0A
#5000000
1!
1.
#10000000
0!
0.
#15000000
1!
1.
#20000000
0!
1"
0.
1/
#25000000
1!
1.
#30000000
0!
b00000000000000010000000000000000 $
b00000000000000100000000000000000 %
b00000000000000001000000000000000 &
1'
0.
b00000000000000010000000000000000 1
b00000000000000100000000000000000 2
b00000000000000001000000000000000 3
14
#35000000
1!
b00000000000000010000000000000000 )
b00000000000000100000000000000000 *
b00000000000000001000000000000000 +
1,
1.
b00000000000000010000000000000000 6
b00000000000000100000000000000000 7
b00000000000000001000000000000000 8
19
b0000000000000010000000000000000000000000000000000000000000000000000000000000000000000000000000000000000000000000000000000000000000000000000000000000000000000000000000000000000000000000000000000000000000000000000000000000000000000000000000000000000000000000000000000000000000000000000000000000000000000000000000000000000000000000000000000000000000000000000000000000000000000000000000000000000000000000000000000000000000000000000000000000000000000000000000000000000000000000000000000000000000000000000000000000000000000000000000000000000000000000000000000000000000000000000000000000000000000000000000000000000000000000000000000000000000000000000000000000000000000000000000000000000000000000000000000000000000000000000000000000000000000000000000000000000000000000000000000000000000000000000000000000000000000000000000000000000000000000000000000000000000000000000000000000000000000000000000000000000000000000000000000000000000000000000000000000000000000000000000000000000000000000000000000000000000000000000000000000000000000000 ;
b0000001110 <
b00000000000000010000000000000000 =
b00000000000000100000000000000000 >
b00000000000000001000000000000000 ?
1@
#40000000
0!
b00000000000000010000000001010000 $
b00000000000000100000000001010000 %
b00000000000000001000000001010000 &
0.
b00000000000000010000000001010000 1
b00000000000000100000000001010000 2
b00000000000000001000000001010000 3
#45000000
1!
b00000000000000010000000001010000 )
b00000000000000100000000001010000 *
b00000000000000001000000001010000 +
0,
1.
b00000000000000010000000001010000 6
b00000000000000100000000001010000 7
b00000000000000001000000001010000 8
09
b00000000000000010000000001010000 =
b00000000000000100000000001010000 >
b00000000000000001000000001010000 ?
0@
1A
#50000000
0!
b00000000000010100000000000000000 $
b00000000000001010000000000000000 %
b00000000000000010000000000000000 &
0.
b00000000000010100000000000000000 1
b00000000000001010000000000000000 2
b00000000000000010000000000000000 3
#55000000
1!
b00000000000010100000000000000000 )
b00000000000001010000000000000000 *
b00000000000000010000000000000000 +
1,
1.
b00000000000010100000000000000000 6
b00000000000001010000000000000000 7
b00000000000000010000000000000000 8
19
b0000000000000010000000000000000000000000000000000000000010000000000000000000000000000000000000000000000000000000000000000000000000000000000000000000000000000000000000000000000000000000000000000000000000000000000000000000000000000000000000000000000000000000000000000000000000000000000000000000000000000000000000000000000000000000000000000000000000000000000000000000000000000000000000000000000000000000000000000000000000000000000000000000000000000000000000000000000000000000000000000000000000000000000000000000000000000000000000000000000000000000000000000000000000000000000000000000000000000000000000000000000000000000000000000000000000000000000000000000000000000000000000000000000000000000000000000000000000000000000000000000000000000000000000000000000000000000000000000000000000000000000000000000000000000000000000000000000000000000000000000000000000000000000000000000000000000000000000000000000000000000000000000000000000000000000000000000000000000000000000000000000000000000000000000000000000000000000000000000000000000000 ;
b0000111000 <
b00000000000010100000000000000000 =
b00000000000001010000000000000000 >
b00000000000000010000000000000000 ?
1@
0A
#60000000
0!
0'
0.
04
#65000000
1!
0,
1.
09
0@
